src/server.py
ic_da_ai-0.1.1.dist-info/METADATA
ic_da_ai-0.1.1.dist-info/WHEEL
ic_da_ai-0.1.1.dist-info/entry_points.txt
ic_da_ai-0.1.1.dist-info/RECORD
