Metadata-Version: 2.4
Name: ic-da-ai
Version: 0.1.1
Summary: IBM Cloud Deployable Architectures MCP Server
Project-URL: Homepage, https://github.com/jonwoodlief/da-ai
Project-URL: Repository, https://github.com/jonwoodlief/da-ai
Project-URL: Issues, https://github.com/jonwoodlief/da-ai/issues
Author-email: Jon Woodlief <jon13w@gmail.com>
License: MIT
Keywords: deployable-architectures,ibm-cloud,infrastructure,mcp
Classifier: Development Status :: 4 - Beta
Classifier: Intended Audience :: Developers
Classifier: License :: OSI Approved :: MIT License
Classifier: Programming Language :: Python :: 3
Classifier: Programming Language :: Python :: 3.10
Classifier: Programming Language :: Python :: 3.11
Classifier: Programming Language :: Python :: 3.12
Classifier: Topic :: Software Development :: Libraries :: Python Modules
Classifier: Topic :: System :: Systems Administration
Requires-Python: >=3.10
Requires-Dist: fastmcp
Requires-Dist: ibm-cloud-sdk-core
Requires-Dist: ibm-platform-services
Requires-Dist: mcp[cli]
